[
  {
    "id": "audience",
    "name": {
      "en": "Audience",
      "ar": "الجمهور"
    },
    "description": {
      "en": "External audience who engage with us from the outside",
      "ar": "الجمهور الخارجي الذي يتفاعل معنا من الخارج"
    },
    "order": 1
  },
  {
    "id": "guests",
    "name": {
      "en": "Guests",
      "ar": "الضيوف"
    },
    "description": {
      "en": "Occasional participants with limited access",
      "ar": "المشاركون المنتظمون ذوي الوصول المحدود"
    },
    "order": 2
  },
  {
    "id": "members",
    "name": {
      "en": "Members",
      "ar": "الأعضاء"
    },
    "description": {
      "en": "Active, permanent participants in the community",
      "ar": "المشاركون النشطون والدائمين في المجتمع"
    },
    "order": 3
  },
  {
    "id": "group-advisory",
    "name": {
      "en": "Group Advisory (GAs)",
      "ar": "المستشارون الجماعيون (GAs)"
    },
    "description": {
      "en": "Leaders who support and guide members",
      "ar": "القادة الذين يدعمون ويرشدون الأعضاء"
    },
    "order": 4
  },
  {
    "id": "lead-group-advisory",
    "name": {
      "en": "Lead Group Advisory (LGAs)",
      "ar": "قادة المستشارين الجماعيين (LGAs)"
    },
    "description": {
      "en": "Guide both the Group Advisory and members",
      "ar": "يرشدون كلاً من المستشارين الجماعيين والأعضاء"
    },
    "order": 5
  },
  {
    "id": "executives",
    "name": {
      "en": "Executives",
      "ar": "التنفيذيون"
    },
    "description": {
      "en": "Set strategic direction and oversee all layers",
      "ar": "يحددون الاتجاه الاستراتيجي ويشرفون على جميع المستويات"
    },
    "order": 6
  }
]
